{
    "transporter":null,
    "tsdf":{
        "epaSiteId":"OHR000116806",
        "siteName":"ABC CORP.",
        "contactPhoneNumber":"866-866-8666",
        "contactPhoneNumberExt":"333",
        "address":{
            
        },
        "siteAddress":{
            "street":"946 N 13TH ST",
            "city":"SEBRING",
            "state":"OH",
            "zip":"10002"
        },
        "emergencyPhone":null,
        "emergencyPhoneExt":null,
        "id":2
    },
    "generator":{
        "epaSiteId":"VAR000525113",
        "siteName":"AUTO BODY REPAIR",
        "contactPhoneNumber":"555-555-5555",
        "contactPhoneNumberExt":"333",
        "address":{
            "street":"88112 SOUTH AVENUE",
            "city":"ALEXANDRIA",
            "state":"VA",
            "zip":"10001"
        },
        "siteAddress":{
            "street":"88112 SOUTH AVENUE",
            "city":"ALEXANDRIA",
            "state":"VA",
            "zip":"10001"
        },
        "emergencyPhone":"555-555-5555",
        "emergencyPhoneExt":"333",
        "id":1,
        "signature": {
            "printedName": null,
            "signatureDate": null
        }
    },
    "status":{
        "id":1,
        "code":"Draft",
        "description":"Visible only to users registered for this site",
        "icon":"fa-star-half-o",
        "order":1
    },
    "manifestTrackingNumber":"861438851ELC",
    "updatedDate":"10/05/2016",
    "certifiedDate":null,
    "createdBy":{
        "firstName":"Jane",
        "lastName":"Doe"
    },
    "updatedBy":{
        "firstName":"John",
        "lastName":"Smith"
    },
    "createdDate":"09/28/2016",
    "handlingInstructions":null,
    "internationalShipment":null,
    "internationalShipmentInfo":{
        "importToUs":null,
        "city":null,
        "state":null,
        "dateLeaving":null,
        "consentNumber":null
    },
    "wasteSection":{
        "wasteCollection":[
            {
                "lineNumber": 1,
                "isHazardous":true,
                "federalHazCodes":[
                    "D001",
                    "D002"
                ],
                "stateGenHazCodes":[
                    "U404"
                ],
                "stateTsdfHazCodes":[
                    "U404"
                ],
                "handlerComments":[
                    
                ],
                "dotDescription":{
                    "shippingName":{
                        "hazardClass":["2.2"],
                        "packingGroup":null,
                        "shippingName":"1,1,1,2-Tetrafluoroethane or Refrigerant gas R 134a",
                        "unIDNumber":["UN3159"],
                        "emergencyGuideNumber": "126"                        
                    },
                    "hazardClass":null,
                    "packingGroup":null,
                    "unIdNumber":null,
                    "additionalDotInformation":"UN3159, 1,1,1,2-Tetrafluoroethane or Refrigerant gas R 134a, 2.2",                    
                    "wasteDescription":null,
                    "erResponseGuidebookNumber":"1234567890",
                    "emergencyPhone":"555-555-5555",
                    "emergencyPhoneExt":null
                },
                "containerInfo":{
                    "number":"8",
                    "type":{
                        "code":"CY",
                        "description":"Cylinders"
                    },
                    "notListedType":null,
                    "quantity":"880",
                    "unit":{
                        "code":"P",
                        "description":"Pounds"
                    },
                    "density":null
                },
                "formCode":null,
                "formCodeComment":null,
                "sourceCode":null,
                "sourceCodeComment":null,
                "managementCode":{
                    "code":"H040",
                    "description":"INCINERATION"
                },
                "managementCodeComment":null,
                "specialHandlingInstructions":null,
                "provideBRInfo":true
            }
        ]
    },
    "transporters":[
        
    ],
    "waste":[
        
    ],
    "additionalInfo": {
        "originalManifestTrackingNumber": "798765432ELC"
    },
    "handlerComments":[
        
    ],
    "discrepancy": null
}